datagovsg/__init__.py
datagovsg/constants.py
datagovsg/datagovsg.py
datagovsg/exceptions.py
datagovsg/py.typed
datagovsg/timezone.py
datagovsg/types.py
datagovsg/ckan/__init__.py
datagovsg/ckan/client.py
datagovsg/economy/__init__.py
datagovsg/economy/client.py
datagovsg/economy/constants.py
datagovsg/economy/types.py
datagovsg/economy/types_args.py
datagovsg/environment/__init__.py
datagovsg/environment/client.py
datagovsg/environment/constants.py
datagovsg/environment/types.py
datagovsg/environment/types_args.py
datagovsg/housing/__init__.py
datagovsg/housing/client.py
datagovsg/housing/constants.py
datagovsg/housing/types.py
datagovsg/housing/types_args.py
datagovsg/transport/__init__.py
datagovsg/transport/client.py
datagovsg/transport/constants.py
datagovsg/transport/types.py
datagovsg/transport/types_args.py
datagovsg-2.0.0.dist-info/LICENSE.txt
datagovsg-2.0.0.dist-info/METADATA
datagovsg-2.0.0.dist-info/WHEEL
datagovsg-2.0.0.dist-info/top_level.txt
datagovsg-2.0.0.dist-info/RECORD
