Metadata-Version: 2.2
Name: datagovsg
Version: 2.0.0
Summary: Python package for interacting with APIs available at Data.gov.sg
Author-email: Yuhui <yuhuibc@gmail.com>
License:                     GNU GENERAL PUBLIC LICENSE
Project-URL: Homepage, https://github.com/yuhui/datagovsg
Project-URL: Documentation, https://datagovsg.readthedocs.io/en/latest/
Project-URL: Repository, https://github.com/yuhui/datagovsg.git
Project-URL: Bug Tracker, https://github.com/yuhui/datagovsg/issues
Project-URL: Changelog, https://github.com/yuhui/datagovsg/blob/master/CHANGELOG.rst
Keywords: datagovsg,data.gov.sg,python,singapore,wrapper
Classifier: Development Status :: 5 - Production/Stable
Classifier: Environment :: Web Environment
Classifier: Intended Audience :: Developers
Classifier: License :: OSI Approved :: GNU General Public License v3 (GPLv3)
Classifier: Natural Language :: English
Classifier: Operating System :: MacOS :: MacOS X
Classifier: Operating System :: Microsoft :: Windows
Classifier: Operating System :: OS Independent
Classifier: Operating System :: POSIX
Classifier: Programming Language :: Python :: 3
Classifier: Topic :: Software Development :: Libraries :: Python Modules
Classifier: Typing :: Typed
Requires-Python: >=3.13
License-File: LICENSE.txt
Requires-Dist: requests
Requires-Dist: requests-cache
Requires-Dist: typeguard
Requires-Dist: types-requests
